sklcc_ssubmit/AppUI.py
sklcc_ssubmit/__init__.py
sklcc_ssubmit/__main__.py
sklcc_ssubmit/sshClient.py
sklcc_ssubmit/ssubmit.py
sklcc_ssubmit/thread_func.py
sklcc_ssubmit_1/AppUI.py
sklcc_ssubmit_1/__init__.py
sklcc_ssubmit_1/__main__.py
sklcc_ssubmit_1/sshClient.py
sklcc_ssubmit_1/ssubmit.py
sklcc_ssubmit_1/thread_func.py
sklcc_ssubmit-0.1.5.dist-info/METADATA
sklcc_ssubmit-0.1.5.dist-info/WHEEL
sklcc_ssubmit-0.1.5.dist-info/top_level.txt
sklcc_ssubmit-0.1.5.dist-info/RECORD
