Metadata-Version: 2.1
Name: sklcc_ssubmit
Version: 0.1.5
Requires-Python: >=3.8
Requires-Dist: bcrypt>=4.0.1
Requires-Dist: cffi>=1.15.1
Requires-Dist: cryptography>=40.0.2
Requires-Dist: paramiko>=3.5.0
Requires-Dist: pycparser>=2.21
Requires-Dist: PyNaCl>=1.5.0
Requires-Dist: tkinterdnd2>=0.4.3
